OuiLookup/__init__.py
OuiLookup/__name__.py
OuiLookup/__version__.py
OuiLookup/logger.py
OuiLookup/main.py
OuiLookup/utils.py
OuiLookup/data/oui.json
OuiLookup/data/oui.txt
ouilookup-0.2.4.data/scripts/ouilookup
tests/__init__.py
tests/test_functions.py
tests/test_trivial.py
ouilookup-0.2.4.dist-info/LICENSE
ouilookup-0.2.4.dist-info/METADATA
ouilookup-0.2.4.dist-info/WHEEL
ouilookup-0.2.4.dist-info/top_level.txt
ouilookup-0.2.4.dist-info/RECORD
