Metadata-Version: 2.1
Name: ouilookup
Version: 0.2.4
Summary: A CLI tool and Python3 module for looking up hardware MAC addresses from the published OUI source at ieee.org.
Home-page: https://github.com/verbnetworks/ouilookup
Author: Verb Networks Pty Ltd
Author-email: contact@verbnetworks.com
License: BSD-2-Clause
Keywords: ouilookup oui mac mac-address hw-address ether ethernet
Platform: UNKNOWN
Classifier: Environment :: Console
Classifier: Intended Audience :: System Administrators
Classifier: Topic :: System :: Networking :: Monitoring
Classifier: Topic :: Software Development :: Libraries :: Python Modules
Classifier: Programming Language :: Python :: 3
Classifier: License :: OSI Approved :: BSD License
